README.rst
setup.py
pylyskom/__init__.py
pylyskom/aio.py
pylyskom/asyncmsg.py
pylyskom/cachedconnection.py
pylyskom/connection.py
pylyskom/datatypes.py
pylyskom/errors.py
pylyskom/komauxitems.py
pylyskom/komsession.py
pylyskom/mimeparse.py
pylyskom/protocol.py
pylyskom/requests.py
pylyskom/stats.py
pylyskom/utils.py
pylyskom/version.py
pylyskom.egg-info/PKG-INFO
pylyskom.egg-info/SOURCES.txt
pylyskom.egg-info/dependency_links.txt
pylyskom.egg-info/requires.txt
pylyskom.egg-info/top_level.txt