Metadata-Version: 2.1
Name: pylyskom
Version: 0.3
Summary: Python LysKOM library
Home-page: https://github.com/osks/pylyskom
Author: Oskar Skoog
Author-email: oskar@osd.se
License: UNKNOWN
Platform: UNKNOWN
Classifier: Intended Audience :: Developers
Classifier: License :: OSI Approved :: GNU General Public License v2 or later (GPLv2+)
Classifier: Programming Language :: Python
Classifier: Topic :: Software Development :: Libraries :: Python Modules
Classifier: Operating System :: OS Independent
Requires-Python: >=3.6
